[{"__type__":"cc.SpriteFrame","content":{"name":"ty_tk_2","rect":{"x":0,"y":0,"width":260,"height":62},"offset":{"x":0,"y":0},"originalSize":{"width":260,"height":62},"rotated":false,"capInsets":[48,16,51,21],"texture":"784jAf4WRLU7tfJTj2+7fh@6c48a"}},[{"__type__":"cc.Prefab","data":{"__id__":1}},{"__type__":"cc.Node","_name":"UITaskReward","_children":[{"__id__":2}],"_components":[{"__type__":"cc.UITransformComponent","node":{"__id__":1},"_contentSize":{"__type__":"cc.Size","width":750,"height":1334}},{"__type__":"cc.WidgetComponent","_name":"hub<WidgetComponent>","node":{"__id__":1},"_alignFlags":45,"_originalWidth":100,"_originalHeight":100},{"__type__":"a41c6Z0mOtIXoZ5efHlMkMK","node":{"__id__":1},"goldicon":{"__id__":10},"gemicon":{"__id__":12},"num":{"__id__":9},"activityicon":{"__id__":14}},{"__type__":"cc.AnimationComponent","_name":"UISetting<AnimationComponent>","node":{"__id__":1},"_clips":[{"__uuid__":"3cwpaigq5BZ5c9MuX2I3KM"}],"_defaultClip":{"__uuid__":"3cwpaigq5BZ5c9MuX2I3KM"}}],"_prefab":{"__type__":"cc.PrefabInfo","root":{"__id__":1},"asset":{"__id__":0},"fileId":"edxfZE6KBAD4v97DBmCntn","_synced":{"default":false,"serializable":false}}},{"__type__":"cc.Node","_name":"board","_parent":{"__id__":1},"_children":[{"__id__":3},{"__id__":4},{"__id__":24}],"_components":[{"__type__":"cc.UITransformComponent","node":{"__id__":2},"_contentSize":{"__type__":"cc.Size","width":750,"height":1334}},{"__type__":"cc.WidgetComponent","_name":"hub<WidgetComponent>","node":{"__id__":2},"_alignFlags":45,"_originalWidth":100,"_originalHeight":100},{"__type__":"cc.ButtonComponent","node":{"__id__":2}}],"_prefab":{"__type__":"cc.PrefabInfo","root":{"__id__":1},"asset":{"__id__":0},"fileId":"13yyiiS4RByLvVPVd0osgG","_synced":{"default":false,"serializable":false}}},{"__type__":"cc.Node","_name":"di","_parent":{"__id__":2},"_components":[{"__type__":"cc.UITransformComponent","_name":"di<UITransformComponent>","node":{"__id__":3},"_contentSize":{"__type__":"cc.Size","width":750,"height":1634}},{"__type__":"cc.SpriteComponent","_name":"di<SpriteComponent>","node":{"__id__":3},"_color":{"__type__":"cc.Color","a":210},"_spriteFrame":{"__uuid__":"31lUfnHZlJR4yYcGzW2F8G@f9941"},"_sizeMode":0},{"__type__":"cc.WidgetComponent","node":{"__id__":3},"_alignFlags":45,"_top":-300,"_originalWidth":750,"_originalHeight":1334},{"__type__":"39b72THTvVOkIHKEr+FCnpw","node":{"__id__":3}}],"_prefab":{"__type__":"cc.PrefabInfo","root":{"__id__":1},"asset":{"__id__":0},"fileId":"85TIsHUipK6Is7xcNdwfij","_synced":{"default":false,"serializable":false}},"_lpos":{"__type__":"cc.Vec3","y":150},"_layer":33554432},{"__type__":"cc.Node","_name":"content","_parent":{"__id__":2},"_children":[{"__id__":5},{"__id__":6},{"__id__":7},{"__id__":10},{"__id__":12},{"__id__":14},{"__id__":16},{"__id__":19},{"__id__":21},{"__id__":22}],"_components":[{"__type__":"cc.UITransformComponent","_name":"content<UITransformComponent>","node":{"__id__":4},"_contentSize":{"__type__":"cc.Size","width":440,"height":618}},{"__type__":"cc.SpriteComponent","_name":"content<SpriteComponent>","node":{"__id__":4},"_spriteFrame":{"__uuid__":"3eO35DEOdB3qIQnz96Cw/d@f9941"},"_type":1,"_sizeMode":0},{"__type__":"cc.ButtonComponent","_name":"content<ButtonComponent>","node":{"__id__":4}}],"_prefab":{"__type__":"cc.PrefabInfo","root":{"__id__":1},"asset":{"__id__":0},"fileId":"90FWXdq99FSpQiWBv085QL","_synced":{"default":false,"serializable":false}},"_lpos":{"__type__":"cc.Vec3","y":20}},{"__type__":"cc.Node","_name":"di-001","_parent":{"__id__":4},"_components":[{"__type__":"cc.UITransformComponent","_name":"di<UITransformComponent>","node":{"__id__":5},"_contentSize":{"__type__":"cc.Size","width":440,"height":618}},{"__type__":"cc.SpriteComponent","_name":"di<SpriteComponent>","node":{"__id__":5},"_spriteFrame":{"__uuid__":"08e/tiFL5LVqCqyhUF32JE@f9941"},"_type":1,"_sizeMode":2,"_isTrimmedMode":false}],"_prefab":{"__type__":"cc.PrefabInfo","root":{"__id__":1},"asset":{"__id__":0},"fileId":"27DKbsBBhL+IOrId9CoOXL","_synced":{"default":false,"serializable":false}},"_layer":33554432},{"__type__":"cc.Node","_name":"name","_parent":{"__id__":4},"_components":[{"__type__":"cc.UITransformComponent","_name":"name<UITransformComponent>","node":{"__id__":6},"_contentSize":{"__type__":"cc.Size","width":100,"height":50.4}},{"__type__":"cc.LabelComponent","_name":"name<LabelComponent>","node":{"__id__":6},"_string":"奖励","_horizontalAlign":0,"_actualFontSize":50,"_fontSize":50,"_isBold":true},{"__type__":"cc.WidgetComponent","_name":"name<WidgetComponent>","node":{"__id__":6},"_alignFlags":16},{"__type__":"b189bSbiyxD0oLK7N07p+n5","node":{"__id__":6},"textid":3009}],"_prefab":{"__type__":"cc.PrefabInfo","root":{"__id__":1},"asset":{"__id__":0},"fileId":"84AEb9lhxPsraqr5t+MaAh","_synced":{"default":false,"serializable":false}},"_lpos":{"__type__":"cc.Vec3","y":264.017},"_layer":33554432},{"__type__":"cc.Node","_name":"numdi","_parent":{"__id__":4},"_children":[{"__id__":8}],"_components":[{"__type__":"cc.UITransformComponent","_name":"rewardcount<UITransformComponent>","node":{"__id__":7},"_contentSize":{"__type__":"cc.Size","width":260,"height":62}},{"__type__":"cc.SpriteComponent","_name":"rewardcount<SpriteComponent>","node":{"__id__":7},"_enabled":false,"_spriteFrame":{"__uuid__":"784jAf4WRLU7tfJTj2+7fh@f9941"}},{"__type__":"cc.WidgetComponent","_name":"rewardcount<WidgetComponent>","node":{"__id__":7},"_alignFlags":36,"_right":90.77800000000002,"_bottom":165.35500000000002}],"_prefab":{"__type__":"cc.PrefabInfo","root":{"__id__":1},"asset":{"__id__":0},"fileId":"92QZeizddMiZzg1OlT2lvD","_synced":{"default":false,"serializable":false}},"_lpos":{"__type__":"cc.Vec3","x":-0.77800000000002,"y":-112.64499999999998},"_layer":33554432},{"__type__":"cc.Node","_name":"num","_parent":{"__id__":7},"_components":[{"__type__":"cc.UITransformComponent","node":{"__id__":8},"_contentSize":{"__type__":"cc.Size","width":110.56,"height":50.4}},{"__id__":9}],"_prefab":{"__type__":"cc.PrefabInfo","root":{"__id__":1},"asset":{"__id__":0},"fileId":"a2ALiFfqpMSIcT3a3qQzpL","_synced":{"default":false,"serializable":false}},"_lpos":{"__type__":"cc.Vec3","y":-2.54},"_layer":33554432},{"__type__":"cc.LabelComponent","node":{"__id__":8},"_string":"钻石×100","_actualFontSize":26,"_fontSize":26,"_isBold":true},{"__type__":"cc.Node","_name":"goldicon","_parent":{"__id__":4},"_children":[{"__id__":11}],"_active":false,"_components":[{"__type__":"cc.UITransformComponent","node":{"__id__":10},"_contentSize":{"__type__":"cc.Size","width":44,"height":48}},{"__type__":"cc.SpriteComponent","node":{"__id__":10},"_sizeMode":2,"_isTrimmedMode":false}],"_prefab":{"__type__":"cc.PrefabInfo","root":{"__id__":1},"asset":{"__id__":0},"fileId":"deiHiNmfRB1ZPK6GP/BWp5","_synced":{"default":false,"serializable":false}},"_lpos":{"__type__":"cc.Vec3","y":62},"_layer":33554432},{"__type__":"cc.Node","_name":"goldicon","_parent":{"__id__":10},"_components":[{"__type__":"cc.UITransformComponent","node":{"__id__":11},"_contentSize":{"__type__":"cc.Size","width":44,"height":48}},{"__type__":"cc.SpriteComponent","node":{"__id__":11}}],"_prefab":{"__type__":"cc.PrefabInfo","root":{"__id__":1},"asset":{"__id__":0},"fileId":"0fXIvRzUFKGbgw6dU2aOyS","_synced":{"default":false,"serializable":false}},"_lpos":{"__type__":"cc.Vec3","x":91.358,"y":-151.0134999999999},"_layer":33554432},{"__type__":"cc.Node","_name":"gemicon","_parent":{"__id__":4},"_children":[{"__id__":13}],"_components":[{"__type__":"cc.UITransformComponent","_name":"gemicon<UITransformComponent>","node":{"__id__":12},"_contentSize":{"__type__":"cc.Size","width":241,"height":146}},{"__type__":"cc.SpriteComponent","_name":"gemicon<SpriteComponent>","node":{"__id__":12},"_spriteFrame":{"__uuid__":"4e9gYjk25BAr9z/7xqZ9lF@f9941"},"_sizeMode":2,"_isTrimmedMode":false}],"_prefab":{"__type__":"cc.PrefabInfo","root":{"__id__":1},"asset":{"__id__":0},"fileId":"04xOKa/6xEmpXLJNPhtxqw","_synced":{"default":false,"serializable":false}},"_lpos":{"__type__":"cc.Vec3","y":34.811},"_layer":33554432},{"__type__":"cc.Node","_name":"gem","_parent":{"__id__":12},"_active":false,"_components":[{"__type__":"cc.UITransformComponent","node":{"__id__":13},"_contentSize":{"__type__":"cc.Size","width":45,"height":43}},{"__type__":"cc.SpriteComponent","node":{"__id__":13},"_spriteFrame":{"__uuid__":"aaLNk34rVKsJT7G3dSbjhs@f9941"},"_sizeMode":2,"_isTrimmedMode":false}],"_prefab":{"__type__":"cc.PrefabInfo","root":{"__id__":1},"asset":{"__id__":0},"fileId":"1d9iHYmJlF1K1CKobj97Ri","_synced":{"default":false,"serializable":false}},"_lpos":{"__type__":"cc.Vec3","x":91.358,"y":-151.0134999999999},"_layer":33554432},{"__type__":"cc.Node","_name":"activityicon","_parent":{"__id__":4},"_children":[{"__id__":15}],"_active":false,"_components":[{"__type__":"cc.UITransformComponent","node":{"__id__":14},"_contentSize":{"__type__":"cc.Size","width":119,"height":116}},{"__type__":"cc.SpriteComponent","node":{"__id__":14},"_spriteFrame":{"__uuid__":"1azcaiDjRLpL+gEkxUonw/@f9941"},"_sizeMode":2,"_isTrimmedMode":false}],"_prefab":{"__type__":"cc.PrefabInfo","root":{"__id__":1},"asset":{"__id__":0},"fileId":"5aJID2SMxJ+pjObaO05042","_synced":{"default":false,"serializable":false}},"_lpos":{"__type__":"cc.Vec3","y":62},"_layer":33554432},{"__type__":"cc.Node","_name":"gem","_parent":{"__id__":14},"_components":[{"__type__":"cc.UITransformComponent","node":{"__id__":15},"_contentSize":{"__type__":"cc.Size","width":66,"height":67}},{"__type__":"cc.SpriteComponent","node":{"__id__":15},"_spriteFrame":{"__uuid__":"43Rhpm91VL943qsLkt+i5u@f9941"}}],"_prefab":{"__type__":"cc.PrefabInfo","root":{"__id__":1},"asset":{"__id__":0},"fileId":"a0lq5CCR5EW4V+2FIKxRI2","_synced":{"default":false,"serializable":false}},"_lpos":{"__type__":"cc.Vec3","x":91.358,"y":-151.0134999999999},"_layer":33554432},{"__type__":"cc.Node","_name":"vediobtn","_parent":{"__id__":4},"_children":[{"__id__":17},{"__id__":18}],"_components":[{"__type__":"cc.UITransformComponent","_name":"rewardbtn<UITransformComponent>","node":{"__id__":16},"_contentSize":{"__type__":"cc.Size","width":260,"height":91}},{"__type__":"cc.SpriteComponent","_name":"vediobtn-001<SpriteComponent>","node":{"__id__":16},"_spriteFrame":{"__uuid__":"0635n+WShEf4WGb2F+5giM@f9941"},"_type":1,"_sizeMode":2,"_isTrimmedMode":false},{"__type__":"cc.ButtonComponent","_name":"vediobtn-001<ButtonComponent>","node":{"__id__":16},"clickEvents":[{"__type__":"cc.ClickEvent","target":{"__id__":1},"_componentId":"a41c6Z0mOtIXoZ5efHlMkMK","handler":"OnClickVedioBtn"},{"__type__":"cc.ClickEvent","target":{"__id__":16},"_componentId":"59f93X9+uJOG4z402hI7edo","handler":"UIPlaySound"}],"_transition":3,"_normalSprite":{"__uuid__":"20g1ukYUVPvKWKBRznAKo+@f9941"},"_hoverSprite":{"__uuid__":"20g1ukYUVPvKWKBRznAKo+@f9941"},"_pressedSprite":{"__uuid__":"54TknWPwVPqJqeCR+Y/Czo@f9941"},"_disabledSprite":{"__uuid__":"95EkngnxZFbYuFpsqVTaFr@f9941"},"_zoomScale":0.8,"_target":{"__id__":16}},{"__type__":"59f93X9+uJOG4z402hI7edo","_name":"vediobtn-001<UIPlaySoundCompont>","node":{"__id__":16},"audioclip":{"__uuid__":"9bdokX8vRPHp3SWaAOVDBk"}}],"_prefab":{"__type__":"cc.PrefabInfo","root":{"__id__":1},"asset":{"__id__":0},"fileId":"beX7v1/FRF77+A4sA0YgtI","_synced":{"default":false,"serializable":false}},"_lpos":{"__type__":"cc.Vec3","y":-246.73},"_layer":33554432},{"__type__":"cc.Node","_name":"vedioicon","_parent":{"__id__":16},"_components":[{"__type__":"cc.UITransformComponent","node":{"__id__":17},"_contentSize":{"__type__":"cc.Size","width":48,"height":36}},{"__type__":"cc.SpriteComponent","node":{"__id__":17},"_spriteFrame":{"__uuid__":"1a5BuWtMFArqc6sSixUPMk@f9941"},"_sizeMode":2,"_isTrimmedMode":false}],"_prefab":{"__type__":"cc.PrefabInfo","root":{"__id__":1},"asset":{"__id__":0},"fileId":"70gBJP7OtFQZduDuFGWPn/","_synced":{"default":false,"serializable":false}},"_lpos":{"__type__":"cc.Vec3","x":-89.13600000000002,"y":7},"_layer":33554432},{"__type__":"cc.Node","_name":"Label","_parent":{"__id__":16},"_components":[{"__type__":"cc.UITransformComponent","_name":"Label<UITransformComponent>","node":{"__id__":18},"_contentSize":{"__type__":"cc.Size","width":160,"height":50.4}},{"__type__":"cc.LabelComponent","_name":"Label<LabelComponent>","node":{"__id__":18},"_color":{"__type__":"cc.Color","r":147,"g":56,"b":24},"_string":"3倍领取","_actualFontSize":30,"_fontSize":30,"_overflow":3,"_enableWrapText":false,"_isBold":true},{"__type__":"b189bSbiyxD0oLK7N07p+n5","node":{"__id__":18},"textid":3067}],"_prefab":{"__type__":"cc.PrefabInfo","root":{"__id__":1},"asset":{"__id__":0},"fileId":"3alkJBYDdGIpJSAboN4CJ1","_synced":{"default":false,"serializable":false}},"_lpos":{"__type__":"cc.Vec3","x":21.25600000000003,"y":4.5},"_layer":33554432},{"__type__":"cc.Node","_name":"normalrewardbtn","_parent":{"__id__":4},"_children":[{"__id__":20}],"_components":[{"__type__":"cc.UITransformComponent","_name":"rewardbtn<UITransformComponent>","node":{"__id__":19},"_contentSize":{"__type__":"cc.Size","width":283,"height":31.422000000000004}},{"__type__":"cc.SpriteComponent","_name":"rewardbtn<SpriteComponent>","node":{"__id__":19},"_enabled":false,"_spriteFrame":{"__uuid__":"52HaF1dOdBTYLo0ke3BsHn@f9941"},"_type":1,"_sizeMode":0},{"__type__":"cc.ButtonComponent","_name":"rewardbtn<ButtonComponent>","node":{"__id__":19},"clickEvents":[{"__type__":"cc.ClickEvent","target":{"__id__":1},"_componentId":"a41c6Z0mOtIXoZ5efHlMkMK","handler":"OnClikRewardBtn"},{"__type__":"cc.ClickEvent","target":{"__id__":19},"_componentId":"59f93X9+uJOG4z402hI7edo","handler":"UIPlaySound"}],"_transition":3,"_normalSprite":{"__uuid__":"20g1ukYUVPvKWKBRznAKo+@f9941"},"_hoverSprite":{"__uuid__":"20g1ukYUVPvKWKBRznAKo+@f9941"},"_pressedSprite":{"__uuid__":"54TknWPwVPqJqeCR+Y/Czo@f9941"},"_disabledSprite":{"__uuid__":"95EkngnxZFbYuFpsqVTaFr@f9941"},"_zoomScale":0.8,"_target":{"__id__":19}},{"__type__":"59f93X9+uJOG4z402hI7edo","_name":"rewardbtn<UIPlaySoundCompont>","node":{"__id__":19},"audioclip":{"__uuid__":"48Ml813Y9MAbEzMqMs/tDI"}}],"_prefab":{"__type__":"cc.PrefabInfo","root":{"__id__":1},"asset":{"__id__":0},"fileId":"49WjPf8UxCeJFt/3mAjT8U","_synced":{"default":false,"serializable":false}},"_lpos":{"__type__":"cc.Vec3","y":-350.072},"_layer":33554432},{"__type__":"cc.Node","_name":"Label","_parent":{"__id__":19},"_components":[{"__type__":"cc.UITransformComponent","_name":"Label<UITransformComponent>","node":{"__id__":20},"_contentSize":{"__type__":"cc.Size","width":96,"height":50.4}},{"__type__":"cc.LabelComponent","_name":"Label<LabelComponent>","node":{"__id__":20},"_string":"普通领取","_actualFontSize":24,"_fontSize":24,"_enableWrapText":false,"_isBold":true,"_isUnderline":true},{"__type__":"b189bSbiyxD0oLK7N07p+n5","node":{"__id__":20},"textid":3069}],"_prefab":{"__type__":"cc.PrefabInfo","root":{"__id__":1},"asset":{"__id__":0},"fileId":"680bk314lGjbAILEz4H+Fc","_synced":{"default":false,"serializable":false}},"_lpos":{"__type__":"cc.Vec3","y":2.099},"_layer":33554432},{"__type__":"cc.Node","_name":"closetishi","_parent":{"__id__":4},"_components":[{"__type__":"cc.UITransformComponent","_name":"closetishi<UITransformComponent>","node":{"__id__":21},"_contentSize":{"__type__":"cc.Size","width":252,"height":63},"_anchorPoint":{"__type__":"cc.Vec2","x":0.5}},{"__type__":"cc.LabelComponent","_name":"closetishi<LabelComponent>","node":{"__id__":21},"_color":{"__type__":"cc.Color","r":255,"g":255,"b":255,"a":230},"_string":"点击空白处关闭","_actualFontSize":36,"_fontSize":36,"_lineHeight":50},{"__type__":"cc.UIOpacityComponent","_name":"closetishi<UIOpacityComponent>","node":{"__id__":21}},{"__type__":"b189bSbiyxD0oLK7N07p+n5","_name":"closetishi<UIText>","node":{"__id__":21},"textid":5016},{"__type__":"cc.WidgetComponent","_name":"closetishi<WidgetComponent>","node":{"__id__":21},"_alignFlags":4,"_bottom":-80}],"_prefab":{"__type__":"cc.PrefabInfo","root":{"__id__":1},"asset":{"__id__":0},"fileId":"f9eQFej+RGiLo1Jj1FOob8","_synced":{"default":false,"serializable":false}},"_lpos":{"__type__":"cc.Vec3","y":-389},"_lscale":{"__type__":"cc.Vec3"},"_layer":33554432},{"__type__":"cc.Node","_name":"closebtn-001","_parent":{"__id__":4},"_children":[{"__id__":23}],"_components":[{"__type__":"cc.UITransformComponent","node":{"__id__":22},"_contentSize":{"__type__":"cc.Size","width":96.827,"height":97.81299999999999}},{"__type__":"cc.ButtonComponent","node":{"__id__":22},"clickEvents":[{"__type__":"cc.ClickEvent","target":{"__id__":1},"_componentId":"a41c6Z0mOtIXoZ5efHlMkMK","handler":"CloseUI"},{"__type__":"cc.ClickEvent","target":{"__id__":22},"_componentId":"59f93X9+uJOG4z402hI7edo","handler":"UIPlaySound"}],"_transition":3,"_normalSprite":{"__uuid__":"20g1ukYUVPvKWKBRznAKo+@f9941"},"_hoverSprite":{"__uuid__":"20g1ukYUVPvKWKBRznAKo+@f9941"},"_pressedSprite":{"__uuid__":"54TknWPwVPqJqeCR+Y/Czo@f9941"},"_disabledSprite":{"__uuid__":"95EkngnxZFbYuFpsqVTaFr@f9941"},"_zoomScale":0.8,"_target":{"__id__":23}},{"__type__":"59f93X9+uJOG4z402hI7edo","_name":"Button<UIPlaySoundCompont>","node":{"__id__":22},"audioclip":{"__uuid__":"48Ml813Y9MAbEzMqMs/tDI"}},{"__type__":"cc.WidgetComponent","_name":"closebtn<WidgetComponent>","node":{"__id__":22},"_alignFlags":33,"_right":1.7910000000000181,"_top":2.2249999999999233}],"_prefab":{"__type__":"cc.PrefabInfo","root":{"__id__":1},"asset":{"__id__":0},"fileId":"c8jSCGGv5B3YE9z9Ukvki5","_synced":{"default":false,"serializable":false}},"_lpos":{"__type__":"cc.Vec3","x":169.79549999999998,"y":257.8685000000001},"_layer":33554432},{"__type__":"cc.Node","_name":"icon","_parent":{"__id__":22},"_components":[{"__type__":"cc.UITransformComponent","node":{"__id__":23},"_contentSize":{"__type__":"cc.Size","width":40,"height":39}},{"__type__":"cc.SpriteComponent","node":{"__id__":23},"_spriteFrame":{"__uuid__":"64vRRwyNNPN56txO8ht4UE@f9941"},"_sizeMode":2,"_isTrimmedMode":false}],"_prefab":{"__type__":"cc.PrefabInfo","root":{"__id__":1},"asset":{"__id__":0},"fileId":"2dzoaKjXtIpJs8WlG+C1l7","_synced":{"default":false,"serializable":false}},"_layer":33554432},{"__type__":"cc.Node","_name":"nativeAd_ts","_parent":{"__id__":2},"_children":[{"__id__":25},{"__id__":26},{"__id__":27}],"_active":false,"_components":[{"__type__":"cc.UITransformComponent","_name":"nativeAd_ts<UITransformComponent>","node":{"__id__":24},"_contentSize":{"__type__":"cc.Size","width":640,"height":360}},{"__type__":"cc.SpriteComponent","_name":"nativeAd_ts<SpriteComponent>","node":{"__id__":24},"_sizeMode":0},{"__type__":"dc797/Y7edLvpA56A54fpcF","_name":"nativeAd_ts<NativeAdTs>","node":{"__id__":24}},{"__type__":"cc.ButtonComponent","_name":"nativeAd_ts<ButtonComponent>","node":{"__id__":24},"clickEvents":[{"__type__":"cc.ClickEvent","target":{"__id__":24},"_componentId":"dc797/Y7edLvpA56A54fpcF","handler":"OnClickAd"}]},{"__type__":"cc.WidgetComponent","_name":"nativeAd_ts<WidgetComponent>","node":{"__id__":24},"_alignFlags":4}],"_prefab":{"__type__":"cc.PrefabInfo","root":{"__id__":1},"asset":{"__id__":0},"fileId":"04g6h0svtGZ7eTbiVL6pGx","_synced":{"default":false,"serializable":false}},"_lpos":{"__type__":"cc.Vec3","y":-487},"_layer":33554432},{"__type__":"cc.Node","_name":"showImg","_parent":{"__id__":24},"_components":[{"__type__":"cc.UITransformComponent","node":{"__id__":25},"_contentSize":{"__type__":"cc.Size","width":640,"height":360}},{"__type__":"cc.SpriteComponent","node":{"__id__":25},"_spriteFrame":{"__uuid__":"b8uNKXm91MgoGwGr9IHnHC@f9941"},"_sizeMode":0}],"_prefab":{"__type__":"cc.PrefabInfo","root":{"__id__":1},"asset":{"__id__":0},"fileId":"dbpA1mnM9AqLHsvSy+sbAi","_synced":{"default":false,"serializable":false}},"_layer":33554432},{"__type__":"cc.Node","_name":"adtip","_parent":{"__id__":24},"_components":[{"__type__":"cc.UITransformComponent","node":{"__id__":26},"_contentSize":{"__type__":"cc.Size","width":46,"height":28}},{"__type__":"cc.SpriteComponent","node":{"__id__":26},"_spriteFrame":{"__uuid__":"04NPl7gvZJUYIcB1/shv2H@f9941"}},{"__type__":"cc.WidgetComponent","_name":"tip<WidgetComponent>","node":{"__id__":26},"_alignFlags":33,"_right":5,"_top":10,"_bottom":10}],"_prefab":{"__type__":"cc.PrefabInfo","root":{"__id__":1},"asset":{"__id__":0},"fileId":"behrJ9+RtLDp9dpS8w18GE","_synced":{"default":false,"serializable":false}},"_lpos":{"__type__":"cc.Vec3","x":292,"y":156},"_layer":33554432},{"__type__":"cc.Node","_name":"closebtn","_parent":{"__id__":24},"_components":[{"__type__":"cc.UITransformComponent","_name":"adtip<UITransformComponent>","node":{"__id__":27},"_contentSize":{"__type__":"cc.Size","width":30,"height":30}},{"__type__":"cc.SpriteComponent","_name":"adtip<SpriteComponent>","node":{"__id__":27},"_spriteFrame":{"__uuid__":"4dxMpVTFlEvpBnJL8v4+4y@f9941"},"_sizeMode":0},{"__type__":"cc.WidgetComponent","_name":"tip<WidgetComponent>","node":{"__id__":27},"_alignFlags":9,"_left":25,"_right":8,"_top":15,"_bottom":10,"_originalWidth":24},{"__type__":"cc.ButtonComponent","node":{"__id__":27},"clickEvents":[{"__type__":"cc.ClickEvent","target":{"__id__":24},"_componentId":"dc797/Y7edLvpA56A54fpcF","handler":"OnClickCloseAD"}],"_transition":3,"_zoomScale":0.9}],"_prefab":{"__type__":"cc.PrefabInfo","root":{"__id__":1},"asset":{"__id__":0},"fileId":"41j2Z12Z5H1KnRTPHKxWPl","_synced":{"default":false,"serializable":false}},"_lpos":{"__type__":"cc.Vec3","x":-280,"y":150},"_layer":33554432}]]
