[[{"__type__":"cc.Prefab","data":{"__id__":1}},{"__type__":"cc.Node","_name":"UITextTIShi","_children":[{"__id__":2}],"_components":[{"__type__":"cc.UITransformComponent","node":{"__id__":1},"_contentSize":{"__type__":"cc.Size","width":750,"height":1334}},{"__type__":"cc.WidgetComponent","_name":"hub<WidgetComponent>","node":{"__id__":1},"_alignFlags":45,"_originalWidth":100,"_originalHeight":100},{"__type__":"cc.AnimationComponent","_name":"UITextTIShi<AnimationComponent>","node":{"__id__":1},"playOnLoad":true,"_clips":[{"__uuid__":"c18QE3691DobaytIkcmMSU"}],"_defaultClip":{"__uuid__":"c18QE3691DobaytIkcmMSU"}},{"__type__":"f89edmKTbtBEYNK2hJJVU+y","node":{"__id__":1},"des":{"__id__":5}},{"__type__":"cc.AnimationComponent","_name":"UISetting<AnimationComponent>","node":{"__id__":1},"_clips":[{"__uuid__":"3cwpaigq5BZ5c9MuX2I3KM"}],"_defaultClip":{"__uuid__":"3cwpaigq5BZ5c9MuX2I3KM"}}],"_prefab":{"__type__":"cc.PrefabInfo","root":{"__id__":1},"asset":{"__id__":0},"fileId":"edxfZE6KBAD4v97DBmCntn","_synced":{"default":false,"serializable":false}}},{"__type__":"cc.Node","_name":"content","_parent":{"__id__":1},"_children":[{"__id__":3},{"__id__":4}],"_components":[{"__type__":"cc.UITransformComponent","_name":"content<UITransformComponent>","node":{"__id__":2},"_contentSize":{"__type__":"cc.Size","width":700,"height":131.289}},{"__type__":"cc.SpriteComponent","_name":"content<SpriteComponent>","node":{"__id__":2},"_color":{"__type__":"cc.Color","r":255,"g":255,"b":255,"a":246},"_spriteFrame":{"__uuid__":"f86iDvg01Ghp3nUsKfL/hS@f9941"},"_type":1,"_sizeMode":0},{"__type__":"cc.ButtonComponent","_name":"content<ButtonComponent>","node":{"__id__":2}}],"_prefab":{"__type__":"cc.PrefabInfo","root":{"__id__":1},"asset":{"__id__":0},"fileId":"c3E/DdgmhEcbBpwxMJkWOB","_synced":{"default":false,"serializable":false}},"_lpos":{"__type__":"cc.Vec3","y":175.0805}},{"__type__":"cc.Node","_name":"name","_parent":{"__id__":2},"_active":false,"_components":[{"__type__":"cc.UITransformComponent","_name":"name<UITransformComponent>","node":{"__id__":3},"_contentSize":{"__type__":"cc.Size","width":88.5022624567956,"height":63}},{"__type__":"cc.LabelComponent","_name":"name<LabelComponent>","node":{"__id__":3},"_color":{"__type__":"cc.Color","r":199,"g":235,"b":246},"_string":"提示","_horizontalAlign":0,"_actualFontSize":40,"_lineHeight":50,"_isItalic":true,"_isBold":true},{"__type__":"cc.WidgetComponent","_name":"name<WidgetComponent>","node":{"__id__":3},"_alignFlags":17,"_top":21.82499999999999}],"_prefab":{"__type__":"cc.PrefabInfo","root":{"__id__":1},"asset":{"__id__":0},"fileId":"65xH3SUX1K1osielTsxaBx","_synced":{"default":false,"serializable":false}},"_lpos":{"__type__":"cc.Vec3","y":87.4},"_layer":33554432},{"__type__":"cc.Node","_name":"des","_parent":{"__id__":2},"_components":[{"__type__":"cc.UITransformComponent","node":{"__id__":4},"_contentSize":{"__type__":"cc.Size","width":540,"height":50.4}},{"__id__":5}],"_prefab":{"__type__":"cc.PrefabInfo","root":{"__id__":1},"asset":{"__id__":0},"fileId":"c4fY5Hx5REvKIS+CgrEvgh","_synced":{"default":false,"serializable":false}},"_lpos":{"__type__":"cc.Vec3","x":1.224,"y":-19.07},"_layer":33554432},{"__type__":"cc.LabelComponent","node":{"__id__":4},"_string":"","_actualFontSize":30,"_fontSize":30,"_overflow":3,"_isBold":true}],{"__type__":"cc.AnimationClip","_name":"texttishianimation","events":[{"frame":1.3333333333333333,"func":"DestroyEvent","params":[]}],"_duration":1.3333333333333333,"_keys":[[0,1,1.1666666666666667,1.3333333333333333],[0,1,1.1666666666666667,1.3333333333333333],[0,1,1.1666666666666667,1.3333333333333333],[0,1,1.1666666666666667,1.3333333333333333],[0,1.1666666666666667,1.3333333333333333]],"_curves":[{"modifiers":[{"__type__":"cc.animation.HierarchyPath","path":"content"},"position"],"data":{"keys":0,"values":[{"__type__":"cc.Vec3","y":100},{"__type__":"cc.Vec3","y":100},{"__type__":"cc.Vec3","y":200},{"__type__":"cc.Vec3","y":300}],"easingMethods":{}}},{"modifiers":["r"],"data":{"keys":1,"values":[255,255,255,255],"easingMethods":{}},"commonTarget":0},{"modifiers":["g"],"data":{"keys":2,"values":[255,255,255,255],"easingMethods":{}},"commonTarget":0},{"modifiers":["b"],"data":{"keys":3,"values":[255,255,255,255],"easingMethods":{}},"commonTarget":0},{"modifiers":["a"],"data":{"keys":4,"values":[255,230,0],"easingMethods":{}},"commonTarget":0}],"_commonTargets":[{"modifiers":[{"__type__":"cc.animation.HierarchyPath","path":"content"},{"__type__":"cc.animation.ComponentPath","component":"cc.SpriteComponent"},"color"]}],"_hash":3042525892}]
